passurakshya/__init__.py
passurakshya/__main__.py
passurakshya/main.py
passurakshya-2.0.1.data/scripts/passurakshya
passurakshya-2.0.1.dist-info/DESCRIPTION.rst
passurakshya-2.0.1.dist-info/METADATA
passurakshya-2.0.1.dist-info/RECORD
passurakshya-2.0.1.dist-info/WHEEL
passurakshya-2.0.1.dist-info/metadata.json
passurakshya-2.0.1.dist-info/top_level.txt
