Metadata-Version: 2.0
Name: passurakshya
Version: 2.0.1
Summary: Save your passwords even safer : 
Home-page: https://github.com/umschaudhary/passurakshya
Author: Umesh Chaudhary
Author-email: umesschaudhary@gmail.com
License: UNKNOWN
Platform: UNKNOWN
Classifier: Environment :: Console
Classifier: Programming Language :: Python :: 3
